LICENSE.txt
README.md
setup.cfg
setup.py
ds_help_utils/__init__.py
ds_help_utils.egg-info/PKG-INFO
ds_help_utils.egg-info/SOURCES.txt
ds_help_utils.egg-info/dependency_links.txt
ds_help_utils.egg-info/requires.txt
ds_help_utils.egg-info/top_level.txt
ds_help_utils/feature_selection/__init__.py
ds_help_utils/feature_selection/_corr_removal.py
ds_help_utils/metrics/__init__.py
ds_help_utils/metrics/_ranking.py
ds_help_utils/utils/__init__.py
ds_help_utils/utils/validation.py