Metadata-Version: 2.1
Name: ds-help-utils
Version: 0.1.1
Summary: A package to help do DS tasks more easily
Home-page: UNKNOWN
Author: Dmitriy Emelianov
Author-email: asdqwer92@gmail.com
License: UNKNOWN
Platform: UNKNOWN
License-File: LICENSE.txt
